open_project_linter-1.0.1.dist-info/DESCRIPTION.rst
open_project_linter-1.0.1.dist-info/METADATA
open_project_linter-1.0.1.dist-info/RECORD
open_project_linter-1.0.1.dist-info/WHEEL
open_project_linter-1.0.1.dist-info/entry_points.txt
open_project_linter-1.0.1.dist-info/metadata.json
open_project_linter-1.0.1.dist-info/top_level.txt
openlinter/__init__.py
openlinter/command_line.py
openlinter/openlinter.py
openlinter/rules.py
openlinter/rules.yml
