Metadata-Version: 2.0
Name: open-project-linter
Version: 1.0.1
Summary: Automatic checklist for open source project best practices.
Home-page: https://github.com/OpenNewsLabs/open-project-linter
Author: Frances Hocutt
Author-email: frances.hocutt+pypi@gmail.com
License: Apache v2.0
Keywords: project linter setup documentation development
Platform: UNKNOWN
Classifier: Development Status :: 3 - Alpha
Classifier: Intended Audience :: Developers
Classifier: Topic :: Software Development :: Documentation
Classifier: Topic :: Software Development :: Version Control
Requires-Dist: gitpython
Requires-Dist: pygments
Requires-Dist: pyyaml
